scoptimize/__init__.py
scoptimize/network.py
scoptimize/utils.py
scoptimize-1.0.1.dist-info/LICENSE
scoptimize-1.0.1.dist-info/METADATA
scoptimize-1.0.1.dist-info/WHEEL
scoptimize-1.0.1.dist-info/top_level.txt
scoptimize-1.0.1.dist-info/RECORD
