Metadata-Version: 2.1
Name: scoptimize
Version: 1.0.1
Summary: Supply Chain Optimization Package
Author-email: Connor Makowski <conmak@mit.edu>
Project-URL: Homepage, https://github.com/connor-makowski/scoptimize
Project-URL: Bug Tracker, https://github.com/connor-makowski/scoptimize/issues
Project-URL: Documentation, https://connor-makowski.github.io/scoptimize/scoptimize.html
Classifier: Programming Language :: Python :: 3
Classifier: License :: OSI Approved :: MIT License
Classifier: Operating System :: OS Independent
Requires-Python: >=3.6
License-File: LICENSE
Requires-Dist: pulp >=2.8.0
Requires-Dist: type-enforced >=0.0.16
